jsonschema_path/__init__.py
jsonschema_path/accessors.py
jsonschema_path/handlers/__init__.py
jsonschema_path/handlers/file.py
jsonschema_path/handlers/protocols.py
jsonschema_path/handlers/requests.py
jsonschema_path/handlers/urllib.py
jsonschema_path/handlers/utils.py
jsonschema_path/loaders.py
jsonschema_path/paths.py
jsonschema_path/py.typed
jsonschema_path/readers.py
jsonschema_path/retrievers.py
jsonschema_path/typing.py
jsonschema_path/utils.py
jsonschema_path-0.3.1.dist-info/LICENSE
jsonschema_path-0.3.1.dist-info/METADATA
jsonschema_path-0.3.1.dist-info/WHEEL
jsonschema_path-0.3.1.dist-info/RECORD
