Metadata-Version: 2.1
Name: jsonschema-path
Version: 0.3.1
Summary: JSONSchema Spec with object-oriented paths
Home-page: https://github.com/p1c2u/jsonschema-path
License: Apache-2.0
Keywords: jsonschema,swagger,spec
Author: Artur Maciag
Author-email: maciag.artur@gmail.com
Requires-Python: >=3.8.0,<4.0.0
Classifier: Development Status :: 4 - Beta
Classifier: Intended Audience :: Developers
Classifier: License :: OSI Approved :: Apache Software License
Classifier: Operating System :: OS Independent
Classifier: Programming Language :: Python :: 3
Classifier: Programming Language :: Python :: 3.8
Classifier: Programming Language :: Python :: 3.9
Classifier: Programming Language :: Python :: 3.10
Classifier: Programming Language :: Python :: 3.11
Classifier: Programming Language :: Python :: 3.12
Classifier: Topic :: Software Development :: Libraries
Classifier: Topic :: Software Development :: Libraries :: Python Modules
Requires-Dist: PyYAML (>=5.1)
Requires-Dist: pathable (>=0.4.1,<0.5.0)
Requires-Dist: referencing (>=0.28.0,<0.31.0)
Requires-Dist: requests (>=2.31.0,<3.0.0)
Project-URL: Repository, https://github.com/p1c2u/jsonschema-path
